{
    "directed": false,
    "multigraph": false,
    "graph": {},
    "nodes": [
        {
            "id": "hizawye AI"
        },
        {
            "id": "knowledge"
        },
        {
            "id": "creativity"
        }
    ],
    "links": [
        {
            "label": "attracted_to",
            "source": "hizawye AI",
            "target": "knowledge"
        },
        {
            "label": "enables",
            "source": "knowledge",
            "target": "creativity"
        }
    ]
}